matrixsh/__init__.py
matrixsh/cli.py
matrixsh/config.py
matrixsh/gateway.py
matrixsh/history.py
matrixsh/install.py
matrixsh/llm.py
matrixsh/pair.py
matrixsh/safety.py
matrixsh/shell.py
matrixsh-0.1.0.dist-info/licenses/LICENSE
matrixsh-0.1.0.dist-info/METADATA
matrixsh-0.1.0.dist-info/WHEEL
matrixsh-0.1.0.dist-info/entry_points.txt
matrixsh-0.1.0.dist-info/top_level.txt
matrixsh-0.1.0.dist-info/RECORD
