Metadata-Version: 2.4
Name: matrixsh
Version: 0.1.0
Summary: MatrixShell: AI-augmented shell wrapper powered by MatrixLLM
Author-email: Ruslan Magana Vsevolodovna <contact@ruslanmv.com>
Maintainer-email: Ruslan Magana Vsevolodovna <contact@ruslanmv.com>
License-Expression: Apache-2.0
Project-URL: Homepage, https://github.com/agent-matrix/MatrixShell
Project-URL: Documentation, https://github.com/agent-matrix/MatrixShell#readme
Project-URL: Repository, https://github.com/agent-matrix/MatrixShell.git
Project-URL: Issues, https://github.com/agent-matrix/MatrixShell/issues
Project-URL: Changelog, https://github.com/agent-matrix/MatrixShell/releases
Keywords: shell,terminal,ai,llm,cli,matrix,assistant
Classifier: Development Status :: 4 - Beta
Classifier: Environment :: Console
Classifier: Intended Audience :: Developers
Classifier: Intended Audience :: System Administrators
Classifier: Operating System :: OS Independent
Classifier: Programming Language :: Python :: 3
Classifier: Programming Language :: Python :: 3.9
Classifier: Programming Language :: Python :: 3.10
Classifier: Programming Language :: Python :: 3.11
Classifier: Programming Language :: Python :: 3.12
Classifier: Programming Language :: Python :: 3.13
Classifier: Topic :: System :: Shells
Classifier: Topic :: Terminals
Classifier: Topic :: Utilities
Classifier: Typing :: Typed
Requires-Python: >=3.9
License-File: LICENSE
Requires-Dist: requests>=2.31.0
Requires-Dist: rich>=13.7.0
Dynamic: license-file
